Flask_Share-0.1.1.dist-info/DESCRIPTION.rst
Flask_Share-0.1.1.dist-info/METADATA
Flask_Share-0.1.1.dist-info/RECORD
Flask_Share-0.1.1.dist-info/WHEEL
Flask_Share-0.1.1.dist-info/metadata.json
Flask_Share-0.1.1.dist-info/top_level.txt
flask_share/__init__.py
flask_share/static/css/share.min.css
flask_share/static/fonts/iconfont.eot
flask_share/static/fonts/iconfont.svg
flask_share/static/fonts/iconfont.ttf
flask_share/static/fonts/iconfont.woff
flask_share/static/js/jquery.share.min.js
flask_share/static/js/social-share.min.js
